odoo/addons/fleet_vehicle_calendar_year/README.rst
odoo/addons/fleet_vehicle_calendar_year/__init__.py
odoo/addons/fleet_vehicle_calendar_year/__manifest__.py
odoo/addons/fleet_vehicle_calendar_year/i18n/fleet_vehicle_calendar_year.pot
odoo/addons/fleet_vehicle_calendar_year/i18n/it.po
odoo/addons/fleet_vehicle_calendar_year/i18n/pt_BR.po
odoo/addons/fleet_vehicle_calendar_year/models/__init__.py
odoo/addons/fleet_vehicle_calendar_year/models/fleet_vehicle.py
odoo/addons/fleet_vehicle_calendar_year/readme/CONTRIBUTORS.rst
odoo/addons/fleet_vehicle_calendar_year/readme/CREDITS.rst
odoo/addons/fleet_vehicle_calendar_year/readme/DESCRIPTION.rst
odoo/addons/fleet_vehicle_calendar_year/static/description/banner.png
odoo/addons/fleet_vehicle_calendar_year/static/description/icon.png
odoo/addons/fleet_vehicle_calendar_year/static/description/index.html
odoo/addons/fleet_vehicle_calendar_year/views/fleet_vehicle.xml
odoo13_addon_fleet_vehicle_calendar_year-13.0.1.0.1.dev6.dist-info/METADATA
odoo13_addon_fleet_vehicle_calendar_year-13.0.1.0.1.dev6.dist-info/WHEEL
odoo13_addon_fleet_vehicle_calendar_year-13.0.1.0.1.dev6.dist-info/top_level.txt
odoo13_addon_fleet_vehicle_calendar_year-13.0.1.0.1.dev6.dist-info/RECORD
